optimas/__init__.py
optimas/arch/__init__.py
optimas/arch/adapt.py
optimas/arch/base.py
optimas/arch/pipeline.py
optimas/collect/__init__.py
optimas/collect/preference_scorer.py
optimas/collect/process.py
optimas/collect/sample.py
optimas/collect/utils.py
optimas/external/__init__.py
optimas/external/reward_config.py
optimas/external/reward_trainer.py
optimas/external/utils.py
optimas/optim/__init__.py
optimas/optim/args.py
optimas/optim/opro.py
optimas/optim/optimizer.py
optimas/optim/ppo.py
optimas/reward/__init__.py
optimas/reward/callback.py
optimas/reward/dataset.py
optimas/reward/eval.py
optimas/reward/finetune.py
optimas/reward/metrics.py
optimas/reward/model.py
optimas/utils/api.py
optimas/utils/config.py
optimas/utils/device.py
optimas/utils/example.py
optimas/utils/extract_json_reliable.py
optimas/utils/load.py
optimas/utils/logging.py
optimas/utils/lora.py
optimas/utils/numerical.py
optimas/utils/operation.py
optimas/utils/parallel.py
optimas/utils/port.py
optimas/utils/prediction.py
optimas/utils/save.py
optimas/utils/template.py
optimas/utils/api_lib/__init__.py
optimas/utils/api_lib/claude.py
optimas/utils/api_lib/gpt.py
optimas/utils/api_lib/huggingface.py
optimas/utils/llm_lib/__init__.py
optimas/utils/llm_lib/get_llm_embeddings.py
optimas/utils/llm_lib/get_llm_outputs.py
optimas/utils/llm_lib/completion/__init__.py
optimas/utils/llm_lib/completion/claude.py
optimas/utils/llm_lib/completion/gpt.py
optimas/utils/llm_lib/completion/huggingface.py
optimas/utils/llm_lib/embedding/__init__.py
optimas/utils/llm_lib/embedding/gritlm.py
optimas/utils/llm_lib/embedding/llm2vec.py
optimas/utils/llm_lib/embedding/openai.py
optimas/utils/llm_lib/embedding/voyage.py
optimas_ai-0.1.0.dist-info/METADATA
optimas_ai-0.1.0.dist-info/WHEEL
optimas_ai-0.1.0.dist-info/licenses/LICENSE
optimas_ai-0.1.0.dist-info/RECORD
