Metadata-Version: 2.4
Name: optimas-ai
Version: 0.1.0
Summary: Describe your package here
Author-email: Your Name <your@email.com>
License: MIT
License-File: LICENSE
Requires-Python: >=3.8
